{
  "mount-elbert": {
    "peakName": "Mount Elbert",
    "Peak Name": "Mount Elbert",
    "Elevation (ft)": 14438
  },
  "mount-massive": {
    "peakName": "Mount Massive",
    "Peak Name": "Mount Massive",
    "Elevation (ft)": 14421
  },
  "mount-harvard": {
    "peakName": "Mount Harvard",
    "Peak Name": "Mount Harvard",
    "Elevation (ft)": 14420
  },
  "blanca-peak": {
    "peakName": "Blanca Peak",
    "Peak Name": "Blanca Peak",
    "Elevation (ft)": 14345
  },
  "la-plata-peak": {
    "peakName": "La Plata Peak",
    "Peak Name": "La Plata Peak",
    "Elevation (ft)": 14336
  },
  "uncompahgre-peak": {
    "peakName": "Uncompahgre Peak",
    "Peak Name": "Uncompahgre Peak",
    "Elevation (ft)": 14321
  },
  "crestone-peak": {
    "peakName": "Crestone Peak",
    "Peak Name": "Crestone Peak",
    "Elevation (ft)": 14294
  },
  "mount-lincoln": {
    "peakName": "Mount Lincoln",
    "Peak Name": "Mount Lincoln",
    "Elevation (ft)": 14293
  },
  "castle-peak": {
    "peakName": "Castle Peak",
    "Peak Name": "Castle Peak",
    "Elevation (ft)": 14279
  },
  "grays-peak": {
    "peakName": "Grays Peak",
    "Peak Name": "Grays Peak",
    "Elevation (ft)": 14278
  },
  "mount-antero": {
    "peakName": "Mount Antero",
    "Peak Name": "Mount Antero",
    "Elevation (ft)": 14276
  },
  "torreys-peak": {
    "peakName": "Torreys Peak",
    "Peak Name": "Torreys Peak",
    "Elevation (ft)": 14275
  },
  "quandary-peak": {
    "peakName": "Quandary Peak",
    "Peak Name": "Quandary Peak",
    "Elevation (ft)": 14271
  },
  "mount-evans": {
    "peakName": "Mount Evans",
    "Peak Name": "Mount Evans",
    "Elevation (ft)": 14265
  },
  "longs-peak": {
    "peakName": "Longs Peak",
    "Peak Name": "Longs Peak",
    "Elevation (ft)": 14259
  },
  "mount-wilson": {
    "peakName": "Mount Wilson",
    "Peak Name": "Mount Wilson",
    "Elevation (ft)": 14246
  },
  "mount-cameron": {
    "peakName": "Mount Cameron",
    "Peak Name": "Mount Cameron",
    "Elevation (ft)": 14238
  },
  "mount-shavano": {
    "peakName": "Mount Shavano",
    "Peak Name": "Mount Shavano",
    "Elevation (ft)": 14231
  },
  "mount-princeton": {
    "peakName": "Mount Princeton",
    "Peak Name": "Mount Princeton",
    "Elevation (ft)": 14204
  },
  "mount-belford": {
    "peakName": "Mount Belford",
    "Peak Name": "Mount Belford",
    "Elevation (ft)": 14203
  },
  "mount-yale": {
    "peakName": "Mount Yale",
    "Peak Name": "Mount Yale",
    "Elevation (ft)": 14200
  },
  "crestone-needle": {
    "peakName": "Crestone Needle",
    "Peak Name": "Crestone Needle",
    "Elevation (ft)": 14197
  },
  "mount-bross": {
    "peakName": "Mount Bross",
    "Peak Name": "Mount Bross",
    "Elevation (ft)": 14172
  },
  "kit-carson-peak": {
    "peakName": "Kit Carson Peak",
    "Peak Name": "Kit Carson Peak",
    "Elevation (ft)": 14165
  },
  "maroon-peak": {
    "peakName": "Maroon Peak",
    "Peak Name": "Maroon Peak",
    "Elevation (ft)": 14163
  },
  "tabeguache-peak": {
    "peakName": "Tabeguache Peak",
    "Peak Name": "Tabeguache Peak",
    "Elevation (ft)": 14162
  },
  "mount-oxford": {
    "peakName": "Mount Oxford",
    "Peak Name": "Mount Oxford",
    "Elevation (ft)": 14160
  },
  "el-diente-peak": {
    "peakName": "El Diente Peak",
    "Peak Name": "El Diente Peak",
    "Elevation (ft)": 14159
  },
  "mount-democrat": {
    "peakName": "Mount Democrat",
    "Peak Name": "Mount Democrat",
    "Elevation (ft)": 14155
  },
  "mount-sneffels": {
    "peakName": "Mount Sneffels",
    "Peak Name": "Mount Sneffels",
    "Elevation (ft)": 14150
  },
  "capitol-peak": {
    "peakName": "Capitol Peak",
    "Peak Name": "Capitol Peak",
    "Elevation (ft)": 14130
  },
  "pikes-peak": {
    "peakName": "Pikes Peak",
    "Peak Name": "Pikes Peak",
    "Elevation (ft)": 14115
  },
  "snowmass-mountain": {
    "peakName": "Snowmass Mountain",
    "Peak Name": "Snowmass Mountain",
    "Elevation (ft)": 14099
  },
  "sunlight-peak": {
    "peakName": "Sunlight Peak",
    "Peak Name": "Sunlight Peak",
    "Elevation (ft)": 14065
  },
  "windom-peak": {
    "peakName": "Windom Peak",
    "Peak Name": "Windom Peak",
    "Elevation (ft)": 14082
  },
  "mount-eolus": {
    "peakName": "Mount Eolus",
    "Peak Name": "Mount Eolus",
    "Elevation (ft)": 14083
  },
  "challenger-point": {
    "peakName": "Challenger Point",
    "Peak Name": "Challenger Point",
    "Elevation (ft)": 14081
  },
  "mount-columbia": {
    "peakName": "Mount Columbia",
    "Peak Name": "Mount Columbia",
    "Elevation (ft)": 14073
  },
  "missouri-mountain": {
    "peakName": "Missouri Mountain",
    "Peak Name": "Missouri Mountain",
    "Elevation (ft)": 14067
  },
  "humboldt-peak": {
    "peakName": "Humboldt Peak",
    "Peak Name": "Humboldt Peak",
    "Elevation (ft)": 14064
  },
  "mount-bierstadt": {
    "peakName": "Mount Bierstadt",
    "Peak Name": "Mount Bierstadt",
    "Elevation (ft)": 14065
  },
  "conundrum-peak": {
    "peakName": "Conundrum Peak",
    "Peak Name": "Conundrum Peak",
    "Elevation (ft)": 14060
  },
  "handies-peak": {
    "peakName": "Handies Peak",
    "Peak Name": "Handies Peak",
    "Elevation (ft)": 14048
  },
  "culebra-peak": {
    "peakName": "Culebra Peak",
    "Peak Name": "Culebra Peak",
    "Elevation (ft)": 14047
  },
  "ellingwood-point": {
    "peakName": "Ellingwood Point",
    "Peak Name": "Ellingwood Point",
    "Elevation (ft)": 14042
  },
  "mount-lindsey": {
    "peakName": "Mount Lindsey",
    "Peak Name": "Mount Lindsey",
    "Elevation (ft)": 14042
  },
  "north-eolus": {
    "peakName": "North Eolus",
    "Peak Name": "North Eolus",
    "Elevation (ft)": 14039
  },
  "little-bear-peak": {
    "peakName": "Little Bear Peak",
    "Peak Name": "Little Bear Peak",
    "Elevation (ft)": 14037
  },
  "mount-sherman": {
    "peakName": "Mount Sherman",
    "Peak Name": "Mount Sherman",
    "Elevation (ft)": 14036
  },
  "redcloud-peak": {
    "peakName": "Redcloud Peak",
    "Peak Name": "Redcloud Peak",
    "Elevation (ft)": 14034
  },
  "pyramid-peak": {
    "peakName": "Pyramid Peak",
    "Peak Name": "Pyramid Peak",
    "Elevation (ft)": 14018
  },
  "wilson-peak": {
    "peakName": "Wilson Peak",
    "Peak Name": "Wilson Peak",
    "Elevation (ft)": 14017
  },
  "wetterhorn-peak": {
    "peakName": "Wetterhorn Peak",
    "Peak Name": "Wetterhorn Peak",
    "Elevation (ft)": 14015
  },
  "san-luis-peak": {
    "peakName": "San Luis Peak",
    "Peak Name": "San Luis Peak",
    "Elevation (ft)": 14014
  },
  "mount-huron": {
    "peakName": "Mount Huron",
    "Peak Name": "Mount Huron",
    "Elevation (ft)": 14012
  },
  "mount-of-the-holy-cross": {
    "peakName": "Mount of the Holy Cross",
    "Peak Name": "Mount of the Holy Cross",
    "Elevation (ft)": 14011
  },
  "sunshine-peak": {
    "peakName": "Sunshine Peak",
    "Peak Name": "Sunshine Peak",
    "Elevation (ft)": 14007
  },
  "grizzly-peak": {
    "peakName": "Grizzly Peak",
    "Peak Name": "Grizzly Peak",
    "Elevation (ft)": 13988
  },
  "stewart-peak": {
    "peakName": "Stewart Peak",
    "Peak Name": "Stewart Peak",
    "Elevation (ft)": 13989
  },
  "turret-peak": {
    "peakName": "Turret Peak",
    "Peak Name": "Turret Peak",
    "Elevation (ft)": 13835
  },
  "jagged-mountain": {
    "peakName": "Jagged Mountain",
    "Peak Name": "Jagged Mountain",
    "Elevation (ft)": 13824
  },
  "vestal-peak": {
    "peakName": "Vestal Peak",
    "Peak Name": "Vestal Peak",
    "Elevation (ft)": 13864
  },
  "dallas-peak": {
    "peakName": "Dallas Peak",
    "Peak Name": "Dallas Peak",
    "Elevation (ft)": 13809
  },
  "teakettle-mountain": {
    "peakName": "Teakettle Mountain",
    "Peak Name": "Teakettle Mountain",
    "Elevation (ft)": 13819
  },
  "thunder-pyramid": {
    "peakName": "Thunder Pyramid",
    "Peak Name": "Thunder Pyramid",
    "Elevation (ft)": 13932
  },
  "cathedral-peak": {
    "peakName": "Cathedral Peak",
    "Peak Name": "Cathedral Peak",
    "Elevation (ft)": 13943
  },
  "pacific-peak": {
    "peakName": "Pacific Peak",
    "Peak Name": "Pacific Peak",
    "Elevation (ft)": 13950
  },
  "pigeon-peak": {
    "peakName": "Pigeon Peak",
    "Peak Name": "Pigeon Peak",
    "Elevation (ft)": 13772
  },
  "gladstone-peak": {
    "peakName": "Gladstone Peak",
    "Peak Name": "Gladstone Peak",
    "Elevation (ft)": 13913
  },
  "emerald-peak": {
    "peakName": "Emerald Peak",
    "Peak Name": "Emerald Peak",
    "Elevation (ft)": 13891
  },
  "ice-mountain": {
    "peakName": "Ice Mountain",
    "Peak Name": "Ice Mountain",
    "Elevation (ft)": 13951
  },
  "north-maroon-peak": {
    "peakName": "North Maroon Peak",
    "Peak Name": "North Maroon Peak",
    "Elevation (ft)": 14014
  }
}